LICENSE.txt
README.md
setup.py
Topsis_Rishi_102017096.egg-info/PKG-INFO
Topsis_Rishi_102017096.egg-info/SOURCES.txt
Topsis_Rishi_102017096.egg-info/dependency_links.txt
Topsis_Rishi_102017096.egg-info/entry_points.txt
Topsis_Rishi_102017096.egg-info/requires.txt
Topsis_Rishi_102017096.egg-info/top_level.txt
topsis_py/topsis.py