Metadata-Version: 2.1
Name: Topsis-Rishi-102017096
Version: 1.0.0.1
Summary: A Python package implementing TOPSIS technique.
Home-page: UNKNOWN
Author: Rishi Malik
Author-email: rishi39malik@gmail.com
License: MIT
Platform: UNKNOWN
Classifier: License :: OSI Approved :: MIT License
Classifier: Programming Language :: Python :: 3
Classifier: Programming Language :: Python :: 3.7
License-File: LICENSE.txt
